<?xml version="1.0" encoding="utf-8" ?>
<dwsync>
<file name="bootstrap.min.js" server="//PC/www/cabb.edu/" local="130786633840000000" remote="130786633840000000" />
<file name="bootstrap.min.js" server="C:/wamp/www/cabb.edu" local="130786633840000000" remote="130786633840000000" />
<file name="Chart.js" server="//PC/www/cabb.edu/" local="130754883460000000" remote="130754883460000000" />
<file name="Chart.js" server="C:/wamp/www/cabb.edu" local="130754883460000000" remote="130754883460000000" />
<file name="clndr.js" server="//PC/www/cabb.edu/" local="130779946980000000" remote="130779946980000000" />
<file name="clndr.js" server="C:/wamp/www/cabb.edu" local="130779946980000000" remote="130779946980000000" />
<file name="cms_admin.js" server="//PC/www/cabb.edu/" local="131033913900000000" remote="131033913900000000" />
<file name="cms_admin.js" server="C:/wamp/www/cabb.edu" local="129898585100000000" remote="129898585100000000" />
<file name="custom.js" server="//PC/www/cabb.edu/" local="130800701760000000" remote="130800701760000000" />
<file name="custom.js" server="C:/wamp/www/cabb.edu" local="130800701760000000" remote="130800701760000000" />
<file name="d3.v3.js" server="//PC/www/cabb.edu/" local="130801525280000000" remote="130801525280000000" />
<file name="d3.v3.js" server="C:/wamp/www/cabb.edu" local="130801525280000000" remote="130801525280000000" />
<file name="jquery.min.js" server="//PC/www/cabb.edu/" local="130778070000000000" remote="130778070000000000" />
<file name="jquery.min.js" server="C:/wamp/www/cabb.edu" local="130778070000000000" remote="130778070000000000" />
<file name="jquery.vmap.js" server="//PC/www/cabb.edu/" local="130780792360000000" remote="130780792360000000" />
<file name="jquery.vmap.js" server="C:/wamp/www/cabb.edu" local="130780792360000000" remote="130780792360000000" />
<file name="jquery.vmap.sampledata.js" server="//PC/www/cabb.edu/" local="130780793220000000" remote="130780793220000000" />
<file name="jquery.vmap.sampledata.js" server="C:/wamp/www/cabb.edu" local="130780793220000000" remote="130780793220000000" />
<file name="jquery.vmap.world.js" server="//PC/www/cabb.edu/" local="130780792820000000" remote="130780792820000000" />
<file name="jquery.vmap.world.js" server="C:/wamp/www/cabb.edu" local="130780792820000000" remote="130780792820000000" />
<file name="metisMenu.min.js" server="//PC/www/cabb.edu/" local="130800696100000000" remote="130800696100000000" />
<file name="metisMenu.min.js" server="C:/wamp/www/cabb.edu" local="130800696100000000" remote="130800696100000000" />
<file name="moment-2.2.1.js" server="//PC/www/cabb.edu/" local="130779946920000000" remote="130779946920000000" />
<file name="moment-2.2.1.js" server="C:/wamp/www/cabb.edu" local="130779946920000000" remote="130779946920000000" />
<file name="rickshaw.js" server="//PC/www/cabb.edu/" local="130801569740000000" remote="130801569740000000" />
<file name="rickshaw.js" server="C:/wamp/www/cabb.edu" local="130801569740000000" remote="130801569740000000" />
<file name="site.js" server="//PC/www/cabb.edu/" local="130779947020000000" remote="130779947020000000" />
<file name="site.js" server="C:/wamp/www/cabb.edu" local="130779947020000000" remote="130779947020000000" />
<file name="underscore-min.js" server="//PC/www/cabb.edu/" local="130779946840000000" remote="130779946840000000" />
<file name="underscore-min.js" server="C:/wamp/www/cabb.edu" local="130779946840000000" remote="130779946840000000" />
</dwsync>